setup.py
avoid_disaster/__init__.py
avoid_disaster.egg-info/PKG-INFO
avoid_disaster.egg-info/SOURCES.txt
avoid_disaster.egg-info/dependency_links.txt
avoid_disaster.egg-info/top_level.txt
test/__init__.py
test/test.py