Metadata-Version: 1.0
Name: avoid_disaster
Version: 1.3
Summary: Script backups easily to Amazon S3
Home-page: http://www.amix.dk/
Author: amix
Author-email: amix@amix.dk
License: BSD
Keywords: backups amazon s3
Platform: Any
Classifier: Development Status :: 5 - Production/Stable
Classifier: Intended Audience :: Developers
Classifier: License :: OSI Approved :: BSD License
Classifier: Operating System :: OS Independent
Classifier: Programming Language :: Python
Classifier: Topic :: Software Development :: Libraries :: Python Modules
